setup.py
spell_messenger_client/__init__.py
spell_messenger_client/__main__.py
spell_messenger_client/main.py
spell_messenger_client.egg-info/PKG-INFO
spell_messenger_client.egg-info/SOURCES.txt
spell_messenger_client.egg-info/dependency_links.txt
spell_messenger_client.egg-info/entry_points.txt
spell_messenger_client.egg-info/not-zip-safe
spell_messenger_client.egg-info/requires.txt
spell_messenger_client.egg-info/top_level.txt
spell_messenger_client/client/__init__.py
spell_messenger_client/client/client.py
spell_messenger_client/client/client_gui.py
spell_messenger_client/client/decorators.py
spell_messenger_client/client/descriptors.py
spell_messenger_client/client/exceptions.py
spell_messenger_client/client/handlers.py
spell_messenger_client/client/metaclasses.py
spell_messenger_client/client/settings.py
spell_messenger_client/client/db/__init__.py
spell_messenger_client/client/db/models.py
spell_messenger_client/client/db/repository.py
spell_messenger_client/client/log/__init__.py
spell_messenger_client/client/log/config.py
spell_messenger_client/jim/__init__.py
spell_messenger_client/jim/config.py
spell_messenger_client/jim/utils.py