Metadata-Version: 1.0
Name: spell-messenger-client
Version: 4.0
Summary: Spell messenger - Client package
Home-page: https://github.com/SPELLGIRL/PyQT
Author: Antonina Kletskina
Author-email: chepushilka@yandex.ru
License: UNKNOWN
Platform: UNKNOWN
